[
  {
    "builtin": true,
    "collection": "PrivacyEx",
    "group": "Hide.VPN.State",
    "name": "VPN/NetworkInterface.getName",
    "author": "OBC,VD171",
    "className": "java.net.NetworkInterface",
    "methodName": "getName",
    "parameterTypes": [ ],
    "returnType": "java.lang.String",
    "minSdk": 4,
    "maxSdk": 999,
    "version": 1,
    "description": "",
    "enabled":true,
    "optional":false,
    "usage":true,
    "notify":false,
    "luaScript": "@spoof_vpn_networkinterface_getname"
  },
  {
    "builtin": true,
    "collection": "PrivacyEx",
    "group": "Hide.VPN.State",
    "name": "VPN/NetworkInterface.getDisplayName",
    "author": "VD171",
    "className": "java.net.NetworkInterface",
    "methodName": "getDisplayName",
    "parameterTypes": [ ],
    "returnType": "java.lang.String",
    "minSdk": 1,
    "maxSdk": 999,
    "version": 1,
    "description": "",
    "enabled":true,
    "optional":false,
    "usage":true,
    "notify":false,
    "luaScript": "@spoof_vpn_networkinterface_getname"
  },
  {
    "builtin": true,
    "collection": "PrivacyEx",
    "group": "Hide.VPN.State",
    "name": "VPN/NetworkInfo.toString",
    "author": "VD171",
    "className": "android.net.NetworkInfo",
    "methodName": "toString",
    "parameterTypes": [ ],
    "returnType": "java.lang.String",
    "minSdk": 1,
    "maxSdk": 999,
    "version": 1,
    "description": "",
    "enabled":true,
    "optional":false,
    "usage":true,
    "notify":false,
    "luaScript": "@spoof_vpn_networkinfo_tostring"
  },
  {
    "builtin": true,
    "collection": "PrivacyEx",
    "group": "Hide.VPN.State",
    "name": "VPN/NetworkInterface.isVirtual",
    "author": "VD171",
    "className": "java.net.NetworkInterface",
    "methodName": "isVirtual",
    "parameterTypes": [ ],
    "returnType": "boolean",
    "minSdk": 1,
    "maxSdk": 999,
    "version": 1,
    "description": "",
    "enabled":true,
    "optional":false,
    "usage":true,
    "notify":false,
    "luaScript": "@spoof_networkinterface_isvirtual"
  },
  {
    "builtin": true,
    "collection": "PrivacyEx",
    "group": "Hide.VPN.State",
    "name": "VPN/NetworkCapabilities.getCapabilities",
    "author": "OBC,VD171",
    "className": "android.net.NetworkCapabilities",
    "methodName": "getCapabilities",
    "parameterTypes": [ ],
    "returnType": "[I",
    "minSdk": 4,
    "maxSdk": 999,
    "version": 1,
    "description": "",
    "enabled":true,
    "optional":false,
    "usage":true,
    "notify":false,
    "luaScript": "@spoof_networkcapabilities_getcapabilities"
  },
  {
    "builtin": true,
    "collection": "PrivacyEx",
    "group": "Hide.VPN.State",
    "name": "VPN/NetworkCapabilities.hasCapability",
    "author": "OBC,VD171",
    "className": "android.net.NetworkCapabilities",
    "methodName": "hasCapability",
    "parameterTypes": [ "int" ],
    "returnType": "boolean",
    "minSdk": 21,
    "maxSdk": 999,
    "version": 1,
    "description": "",
    "enabled":true,
    "optional":false,
    "usage":true,
    "notify":false,
    "luaScript": "@spoof_networkcapabilities_hascapabilities"
  },
  {
    "builtin": true,
    "collection": "PrivacyEx",
    "group": "Hide.VPN.State",
    "name": "VPN/NetworkInfo.getState",
    "author": "VD171",
    "className": "android.net.NetworkInfo",
    "methodName": "getState",
    "parameterTypes": [ ],
    "returnType": "android.net.NetworkInfo$State",
    "minSdk": 1,
    "maxSdk": 999,
    "version": 1,
    "description": "",
    "enabled":true,
    "optional":false,
    "usage":true,
    "notify":false,
    "luaScript": "@spoof_vpn_networkinfo_getstate"
  },
  {
    "builtin": true,
    "collection": "PrivacyEx",
    "group": "Hide.VPN.State",
    "name": "VPN/NetworkInfo.getReason",
    "author": "VD171",
    "className": "android.net.NetworkInfo",
    "methodName": "getReason",
    "parameterTypes": [ ],
    "returnType": "java.lang.String",
    "minSdk": 1,
    "maxSdk": 999,
    "version": 1,
    "description": "",
    "enabled":true,
    "optional":false,
    "usage":true,
    "notify":false,
    "luaScript": "@spoof_vpn_networkinfo_getreason"
  },
  {
    "builtin": true,
    "collection": "PrivacyEx",
    "group": "Hide.VPN.State",
    "name": "VPN/NetworkCapabilities.hasTransport",
    "author": "VD171",
    "className": "android.net.NetworkCapabilities",
    "methodName": "hasTransport",
    "parameterTypes": ["int"],
    "returnType": "boolean",
    "minSdk": 21,
    "maxSdk": 999,
    "version": 1,
    "description": "",
    "enabled":true,
    "optional":false,
    "usage":true,
    "notify":false,
    "luaScript": "@spoof_vpn_networkcapabilities_hastransport"
  },
  {
    "builtin": true,
    "collection": "PrivacyEx",
    "group": "Hide.VPN.State",
    "name": "VPN/ConnectivityManager.getAllNetworkInfo",
    "author": "VD171",
    "className": "android.net.ConnectivityManager",
    "methodName": "getAllNetworkInfo",
    "parameterTypes": [ ],
    "returnType": "[Landroid.net.NetworkInfo;",
    "minSdk": 1,
    "maxSdk": 999,
    "version": 1,
    "description": "",
    "enabled":true,
    "optional":false,
    "usage":true,
    "notify":false,
    "luaScript": "@spoof_vpn_connectivitymanager_getallnetworkinfo"
  },
  {
    "builtin": true,
    "collection": "PrivacyEx",
    "group": "Hide.VPN.State",
    "name": "VPN/ConnectivityManager.getNetworkInfo",
    "author": "VD171",
    "className": "android.net.ConnectivityManager",
    "methodName": "getNetworkInfo",
    "parameterTypes": ["int"],
    "returnType": "android.net.NetworkInfo",
    "minSdk": 1,
    "maxSdk": 999,
    "version": 1,
    "description": "",
    "enabled":true,
    "optional":false,
    "usage":true,
    "notify":false,
    "luaScript": "@spoof_vpn_connectivitymanager_getnetworkinfo"
  },
  {
    "builtin": true,
    "collection": "PrivacyEx",
    "group": "Hide.VPN.State",
    "name": "VPN/NetworkInfo.getDetailedState",
    "author": "VD171",
    "className": "android.net.NetworkInfo",
    "methodName": "getDetailedState",
    "parameterTypes": [ ],
    "returnType": "android.net.NetworkInfo$DetailedState",
    "minSdk": 1,
    "maxSdk": 999,
    "version": 1,
    "description": "",
    "enabled":true,
    "optional":false,
    "usage":true,
    "notify":false,
    "luaScript": "@spoof_vpn_networkinfo_getdetailedstate"
  },
  {
    "builtin": true,
    "collection": "PrivacyEx",
    "group": "Hide.VPN.State",
    "name": "VPN/Inet4Address.getHostAddress",
    "author": "VD171",
    "className": "java.net.Inet4Address",
    "methodName": "getHostAddress",
    "parameterTypes": [ ],
    "returnType": "java.lang.String",
    "minSdk": 1,
    "maxSdk": 999,
    "version": 1,
    "description": "",
    "enabled":true,
    "optional":false,
    "usage":true,
    "notify":false,
    "luaScript": "@spoof_vpn_inetaddress_gethost"
  },
  {
    "builtin": true,
    "collection": "PrivacyEx",
    "group": "Hide.VPN.State",
    "name": "VPN/Inet6Address.getHostAddress",
    "author": "VD171",
    "className": "java.net.Inet6Address",
    "methodName": "getHostAddress",
    "parameterTypes": [ ],
    "returnType": "java.lang.String",
    "minSdk": 1,
    "maxSdk": 999,
    "version": 1,
    "description": "",
    "enabled":true,
    "optional":false,
    "usage":true,
    "notify":false,
    "luaScript": "@spoof_vpn_inetaddress_gethost"
  },
  {
    "builtin": true,
    "collection": "PrivacyEx",
    "group": "Hide.VPN.State",
    "name": "VPN/InetAddress.getHostAddress",
    "author": "VD171",
    "className": "java.net.InetAddress",
    "methodName": "getHostAddress",
    "parameterTypes": [ ],
    "returnType": "java.lang.String",
    "minSdk": 1,
    "maxSdk": 999,
    "version": 1,
    "description": "",
    "enabled":true,
    "optional":false,
    "usage":true,
    "notify":false,
    "luaScript": "@spoof_vpn_inetaddress_gethost"
  },
  {
    "builtin": true,
    "collection": "PrivacyEx",
    "group": "Hide.VPN.State",
    "name": "VPN/InetAddress.getHostName",
    "author": "VD171",
    "className": "java.net.InetAddress",
    "methodName": "getHostName",
    "parameterTypes": [ ],
    "returnType": "java.lang.String",
    "minSdk": 1,
    "maxSdk": 999,
    "version": 1,
    "description": "",
    "enabled":true,
    "optional":false,
    "usage":true,
    "notify":false,
    "luaScript": "@spoof_vpn_inetaddress_gethost"
  },
  {
    "builtin": true,
    "collection": "PrivacyEx",
    "group": "Hide.VPN.State",
    "name": "VPN/NetworkInfo.getSubtype",
    "author": "VD171",
    "className": "android.net.NetworkInfo",
    "methodName": "getSubtype",
    "parameterTypes": [ ],
    "returnType": "int",
    "minSdk": 1,
    "maxSdk": 999,
    "version": 1,
    "description": "",
    "enabled":true,
    "optional":false,
    "usage":true,
    "notify":false,
    "luaScript": "@spoof_vpn_networkinfo_getsubtype"
  },
  {
    "builtin": true,
    "collection": "PrivacyEx",
    "group": "Hide.VPN.State",
    "name": "VPN/NetworkInterface.getByName",
    "author": "VD171",
    "className": "java.net.NetworkInterface",
    "methodName": "getByName",
    "parameterTypes": ["java.lang.String"],
    "returnType": "java.net.NetworkInterface",
    "minSdk": 1,
    "maxSdk": 999,
    "version": 1,
    "description": "",
    "enabled":true,
    "optional":false,
    "usage":true,
    "notify":false,
    "luaScript": "@spoof_vpn_networkinterface_getname"
  },
  {
    "builtin": true,
    "collection": "PrivacyEx",
    "group": "Hide.VPN.State",
    "name": "VPN/NetworkInfo.isConnected",
    "author": "OBC,VD171",
    "className": "android.net.NetworkInfo",
    "methodName": "isConnected",
    "parameterTypes": [ ],
    "returnType": "boolean",
    "minSdk": 28,
    "maxSdk": 999,
    "version": 1,
    "description": "",
    "enabled":true,
    "optional":false,
    "usage":true,
    "notify":false,
    "luaScript": "@spoof_vpn_networkinfo"
  },
  {
    "builtin": true,
    "collection": "PrivacyEx",
    "group": "Hide.VPN.State",
    "name": "VPN/NetworkInfo.isConnectedOrConnecting",
    "author": "OBC,VD171",
    "className": "android.net.NetworkInfo",
    "methodName": "isConnectedOrConnecting",
    "parameterTypes": [ ],
    "returnType": "boolean",
    "minSdk": 28,
    "maxSdk": 999,
    "version": 1,
    "description": "",
    "enabled":true,
    "optional":false,
    "usage":true,
    "notify":false,
    "luaScript": "@spoof_vpn_networkinfo"
  }
]