[
  {
    "builtin": false,
    "collection": "Log",
    "group": "Log.Shell",
    "name": "Log/ForwardingOs.execv",
    "author": "OBC",
    "className": "libcore.io.ForwardingOs",
    "methodName": "execv",
    "parameterTypes": [ "java.lang.String", "[Ljava.lang.String;" ],
    "returnType": "void",
    "minSdk": 1,
    "maxSdk": 999,
    "version": 1,
    "description": "",
    "enabled":true,
    "optional":true,
    "usage":true,
    "notify":false,
    "luaScript": "@shell_execv_log"
  },
  {
    "builtin": false,
    "collection": "Log",
    "group": "Log.Shell",
    "name": "Log/ForwardingOs.execve",
    "author": "OBC",
    "className": "libcore.io.ForwardingOs",
    "methodName": "execve",
    "parameterTypes": [ "java.lang.String", "[Ljava.lang.String;", "[Ljava.lang.String;" ],
    "returnType": "void",
    "minSdk": 1,
    "maxSdk": 999,
    "version": 1,
    "description": "",
    "enabled":true,
    "optional":true,
    "usage":true,
    "notify":false,
    "luaScript": "@shell_execv_log"
  },

  {
    "builtin": false,
    "collection": "Log",
    "group": "Log.Shell",
    "name": "Log/Os.execv",
    "author": "OBC",
    "className": "android.system.Os",
    "methodName": "execv",
    "parameterTypes": [ "java.lang.String", "[Ljava.lang.String;" ],
    "returnType": "void",
    "minSdk": 1,
    "maxSdk": 999,
    "version": 1,
    "description": "",
    "enabled":true,
    "optional":true,
    "usage":true,
    "notify":false,
    "luaScript": "@shell_execv_log"
  },
  {
    "builtin": false,
    "collection": "Log",
    "group": "Log.Shell",
    "name": "Log/Os.execve",
    "author": "OBC",
    "className": "android.system.Os",
    "methodName": "execve",
    "parameterTypes": [ "java.lang.String", "[Ljava.lang.String;", "[Ljava.lang.String;" ],
    "returnType": "void",
    "minSdk": 1,
    "maxSdk": 999,
    "version": 1,
    "description": "",
    "enabled":true,
    "optional":true,
    "usage":true,
    "notify":false,
    "luaScript": "@shell_execv_log"
  },



  {
    //exec(String command)
    "builtin": true,
    "collection": "PrivacyEx",
    "group": "ID.Shell",
    "name": "ID.Runtime.exec(command)",
    "author": "OBC",
    "className": "java.lang.Runtime",
    "methodName": "exec",
    "parameterTypes": [ "java.lang.String" ],
    "returnType": "java.lang.Process",
    "minSdk": 0,
    "maxSdk": 999,
    "version": 0,
    "description": "",
    "enabled":true,
    "optional":true,
    "usage":true,
    "notify":false,
    "luaScript": "@shell_one_log"
  },

  {
    // exec(String command, String[] envp)
    "builtin": true,
    "collection": "PrivacyEx",
    "group": "ID.Shell",
    "name": "ID.Runtime.exec(command, envp)",
    "author": "OBC",
    "className": "java.lang.Runtime",
    "methodName": "exec",
    "parameterTypes": [ "java.lang.String", "[Ljava.lang.String;" ],
    "returnType": "java.lang.Process",
    "minSdk": 0,
    "maxSdk": 999,
    "version": 0,
    "description": "",
    "enabled":true,
    "optional":true,
    "usage":true,
    "notify":false,
    "luaScript": "@shell_one_log"
  },

  {
    //exec(String command, String[] envp, File dir)
    "builtin": true,
    "collection": "PrivacyEx",
    "group": "ID.Shell",
    "name": "ID.Runtime.exec(command, envp, dir)",
    "author": "OBC",
    "className": "java.lang.Runtime",
    "methodName": "exec",
    "parameterTypes": [ "java.lang.String", "[Ljava.lang.String;", "java.io.File" ],
    "returnType": "java.lang.Process",
    "minSdk": 0,
    "maxSdk": 999,
    "version": 0,
    "description": "",
    "enabled":true,
    "optional":true,
    "usage":true,
    "notify":false,
    "luaScript": "@shell_one_log"
  },

  {
    //exec(String[] cmdarray)
    "builtin": true,
    "collection": "PrivacyEx",
    "group": "ID.Shell",
    "name": "ID.Runtime.exec(commands)",
    "author": "OBC",
    "className": "java.lang.Runtime",
    "methodName": "exec",
    "parameterTypes": [ "[Ljava.lang.String;" ],
    "returnType": "java.lang.Process",
    "minSdk": 0,
    "maxSdk": 999,
    "version": 0,
    "description": "",
    "enabled":true,
    "optional":true,
    "usage":true,
    "notify":false,
    "luaScript": "@shell_two_log"
  },

  {
    //exec(String[] cmdarray, String[] envp)
    "builtin": true,
    "collection": "PrivacyEx",
    "group": "ID.Shell",
    "name": "ID.Runtime.exec(commands, envp)",
    "author": "OBC",
    "className": "java.lang.Runtime",
    "methodName": "exec",
    "parameterTypes": [ "[Ljava.lang.String;", "[Ljava.lang.String;" ],
    "returnType": "java.lang.Process",
    "minSdk": 0,
    "maxSdk": 999,
    "version": 0,
    "description": "",
    "enabled":true,
    "optional":true,
    "usage":true,
    "notify":false,
    "luaScript": "@shell_two_log"
  },

  {
    //exec(String[] cmdarray, String[] envp, File dir)
    "builtin": true,
    "collection": "PrivacyEx",
    "group": "ID.Shell",
    "name": "ID.Runtime.exec(commands, envp, dir)",
    "author": "OBC",
    "className": "java.lang.Runtime",
    "methodName": "exec",
    "parameterTypes": [ "[Ljava.lang.String;", "[Ljava.lang.String;", "java.io.File" ],
    "returnType": "java.lang.Process",
    "minSdk": 0,
    "maxSdk": 999,
    "version": 0,
    "description": "",
    "enabled":true,
    "optional":true,
    "usage":true,
    "notify":false,
    "luaScript": "@shell_two_log"
  },

  {
    //ProcessBuilder.start()
    "builtin": true,
    "collection": "PrivacyEx",
    "group": "ID.Shell",
    "name": "ID.ProcessBuilder.start",
    "author": "OBC",
    "className": "java.lang.ProcessBuilder",
    "methodName": "start",
    "parameterTypes": [ ],
    "returnType": "java.lang.Process",
    "minSdk": 0,
    "maxSdk": 999,
    "version": 0,
    "description": "",
    "enabled":true,
    "optional":true,
    "usage":true,
    "notify":false,
    "luaScript": "@shell_three_log"
  }
]